README.md
setup.cfg
setup.py
dstoolkit_distributions/Binomialdistribution.py
dstoolkit_distributions/Gaussiandistribution.py
dstoolkit_distributions/Generaldistribution.py
dstoolkit_distributions/__init__.py
dstoolkit_distributions.egg-info/PKG-INFO
dstoolkit_distributions.egg-info/SOURCES.txt
dstoolkit_distributions.egg-info/dependency_links.txt
dstoolkit_distributions.egg-info/not-zip-safe
dstoolkit_distributions.egg-info/top_level.txt