Metadata-Version: 1.0
Name: dstoolkit-distributions
Version: 1.4
Summary: Binomial and Gaussian distributions
Home-page: UNKNOWN
Author: Gustavo Jorge Martins de Aguiar
Author-email: gustavoaguiar@id.uff.br
License: UNKNOWN
Platform: UNKNOWN
